setup.py
django_dummy_plug.egg-info/PKG-INFO
django_dummy_plug.egg-info/SOURCES.txt
django_dummy_plug.egg-info/dependency_links.txt
django_dummy_plug.egg-info/requires.txt
django_dummy_plug.egg-info/top_level.txt
django_dummy_plug.egg-info/zip-safe
dummyplug/__init__.py
dummyplug/storage.py